nbf/__init__.py
nbf/d2d.py
nbf/epc.py
nbf/gitcolab.py
nbf-0.0.5.dist-info/METADATA
nbf-0.0.5.dist-info/WHEEL
nbf-0.0.5.dist-info/licenses/LICENSE
nbf-0.0.5.dist-info/RECORD
