Metadata-Version: 2.1
Name: nbf
Version: 0.0.5
Summary: Notebook Features, systematic stacking and code reuse.
Project-URL: Homepage, https://github.com/Jaciss/nbf
Project-URL: Bug Tracker, https://github.com/Jaciss/nbf/issues
Author-email: Jaciss <nbf@maya.software>
License-File: LICENSE
Classifier: License :: OSI Approved :: MIT License
Classifier: Operating System :: OS Independent
Classifier: Programming Language :: Python :: 3
Requires-Python: >=3.7
